{"options":{"validator":{"$jsonSchema":{"bsonType":"object","required":["employeeId","dateChange","basicSalary","curType","note"],"properties":{"employeeId":{"bsonType":"string","minLength":{"$numberInt":"5"},"maxLength":{"$numberInt":"30"},"description":"employeeId must be string"},"dateChange":{"bsonType":"date","description":"dateChange must be date"},"basicSalary":{"bsonType":"double","description":"basicSalary must be double"},"curType":{"bsonType":"string","enum":["VND","USD"],"description":"curType must be string and in (VND,USD)"},"note":{"bsonType":["null","string"],"description":"note must be string"}}}},"validationLevel":"strict","validationAction":"error"},"indexes":[{"v":{"$numberInt":"2"},"key":{"_id":{"$numberInt":"1"}},"name":"_id_"}],"uuid":"f4324a45a4904a68a96ee0fe57953ec9","collectionName":"tblempSalary","type":"collection"}